riskmatrix/__init__.py
riskmatrix/axis.py
riskmatrix/category.py
riskmatrix/coordinate.py
riskmatrix/matrix.py
riskmatrix-0.0.13.dist-info/AUTHORS.rst
riskmatrix-0.0.13.dist-info/LICENSE
riskmatrix-0.0.13.dist-info/METADATA
riskmatrix-0.0.13.dist-info/WHEEL
riskmatrix-0.0.13.dist-info/top_level.txt
riskmatrix-0.0.13.dist-info/RECORD
