Metadata-Version: 2.1
Name: riskmatrix
Version: 0.0.13
Summary: A package to deal with risk matrix data.
Home-page: https://github.com/slicerisk/riskmatrix
Author: Alex de Ruijter
Author-email: alex@slicerisk.com
License: GNU General Public License v3
Keywords: riskmatrix
Platform: UNKNOWN
Classifier: Development Status :: 2 - Pre-Alpha
Classifier: Intended Audience :: Developers
Classifier: License :: OSI Approved :: GNU General Public License v3 (GPLv3)
Classifier: Natural Language :: English
Classifier: Programming Language :: Python :: 3
Classifier: Programming Language :: Python :: 3.7
